hi_tension-0.1.0.dist-info/METADATA
hi_tension-0.1.0.dist-info/WHEEL
hi_tension.pyd
hi_tension-0.1.0.dist-info/RECORD
