Metadata-Version: 2.1
Name: hi_tension
Version: 0.1.0
Requires-Dist: numpy>=1.18.4
Summary: Basic but fast network communication between scientific applications
Author: gggto <47183108+gggto@users.noreply.github.com>
Author-Email: gggto <47183108+gggto@users.noreply.github.com>
License: MIT
Requires-Python: >=3.6
Project-URL: Repository, https://github.com/gggto/py-hi-tension
